wrdstopg/__init__.py
wrdstopg/wrdstopg.py
wrdstopg-0.0.9.dist-info/METADATA
wrdstopg-0.0.9.dist-info/RECORD
wrdstopg-0.0.9.dist-info/WHEEL
wrdstopg-0.0.9.dist-info/top_level.txt
