Metadata-Version: 2.1
Name: wrdstopg
Version: 0.0.9
Summary: Download wrds tables and upload to PostgreSQL, upload SAS file to PG
Home-page: https://github.com/iangow-public/wrds_pg/
Author: Ian Gow
Author-email: ian.gow@unimelb.edu.au
License: UNKNOWN
Platform: UNKNOWN
Classifier: Programming Language :: Python :: 3
Classifier: License :: OSI Approved :: MIT License
Classifier: Operating System :: OS Independent
Requires-Python: >=3
Requires-Dist: pandas
Requires-Dist: sqlalchemy
Requires-Dist: paramiko
